README.rst
setup.py
semantics3/__init__.py
semantics3/categories.py
semantics3/error.py
semantics3/offers.py
semantics3/products.py
semantics3/semantics3.py
semantics3.egg-info/PKG-INFO
semantics3.egg-info/SOURCES.txt
semantics3.egg-info/dependency_links.txt
semantics3.egg-info/requires.txt
semantics3.egg-info/top_level.txt